umsgpack.py
u_msgpack_python-2.7.0.dist-info/LICENSE
u_msgpack_python-2.7.0.dist-info/METADATA
u_msgpack_python-2.7.0.dist-info/WHEEL
u_msgpack_python-2.7.0.dist-info/top_level.txt
u_msgpack_python-2.7.0.dist-info/RECORD
