Metadata-Version: 1.1
Name: u-msgpack-python
Version: 2.7.0
Summary: A portable, lightweight MessagePack serializer and deserializer written in pure Python.
Home-page: https://github.com/vsergeev/u-msgpack-python
Author: vsergeev
Author-email: v@sergeev.io
License: MIT
Keywords: msgpack serialization deserialization
Platform: UNKNOWN
Classifier: Development Status :: 5 - Production/Stable
Classifier: License :: OSI Approved :: MIT License
Classifier: Operating System :: OS Independent
Classifier: Programming Language :: Python
Classifier: Programming Language :: Python :: 2
Classifier: Programming Language :: Python :: 3
Classifier: Programming Language :: Python :: Implementation :: CPython
Classifier: Programming Language :: Python :: Implementation :: PyPy
